npc_lims/__init__.py
npc_lims/exceptions.py
npc_lims/py.typed
npc_lims/jobs/__init__.py
npc_lims/jobs/queue.py
npc_lims/metadata/__init__.py
npc_lims/metadata/codeocean_utils.py
npc_lims/metadata/nwb.sql
npc_lims/metadata/spreadsheets.py
npc_lims/metadata/targeting.py
npc_lims/metadata/types.py
npc_lims/paths/__init__.py
npc_lims/paths/cache.py
npc_lims/paths/codeocean_s3.py
npc_lims/paths/s3.py
npc_lims/scripts/__init__.py
npc_lims/scripts/generate_session_video_data_assets.py
npc_lims/scripts/process_queue.py
npc_lims/scripts/regenerate_all_nwbs.py
npc_lims/scripts/run_session_cache_capsule.py
npc_lims/scripts/run_spike_sorting.py
npc_lims/scripts/run_video_processing.py
npc_lims/scripts/update_session_status.py
npc_lims/scripts/update_session_video_data_asset_permissions.py
npc_lims/status/__init__.py
npc_lims/status/behavior_sessions.py
npc_lims/status/tracked_sessions.py
npc_lims-0.1.190.dist-info/licenses/LICENSE
npc_lims-0.1.190.dist-info/METADATA
npc_lims-0.1.190.dist-info/WHEEL
npc_lims-0.1.190.dist-info/entry_points.txt
npc_lims-0.1.190.dist-info/top_level.txt
npc_lims-0.1.190.dist-info/RECORD
