Metadata-Version: 2.4
Name: npc_lims
Version: 0.1.190
Summary: Tools to fetch and update paths, metadata and state for Mindscope Neuropixels sessions, in the cloud.
Author-email: Arjun Sridhar <arjun.sridhar@alleninstitute.org>, Ben Hardcastle <ben.hardcastle@alleninstitute.org>
License: MIT
Project-URL: Repository, https://github.com/AllenInstitute/npc_lims
Project-URL: Issues, https://github.com/AllenInstitute/npc_lims/issues
Classifier: Programming Language :: Python :: 3
Classifier: Programming Language :: Python :: 3.9
Classifier: Programming Language :: Python :: 3.10
Classifier: Programming Language :: Python :: 3.11
Classifier: License :: OSI Approved :: MIT License
Classifier: Operating System :: Microsoft :: Windows
Classifier: Operating System :: POSIX :: Linux
Requires-Python: >=3.9
License-File: LICENSE
Requires-Dist: npc-session>=0.1.36
Requires-Dist: redis>=4.1.4
Requires-Dist: pydbhub-bjh>=0.0.8
Requires-Dist: pyyaml>=6.0.1
Requires-Dist: pyopenssl>=23.2.0
Requires-Dist: openpyxl>=3.1.2
Requires-Dist: packaging>=23.2
Requires-Dist: types-pyYAML>=6.0.12.12
Requires-Dist: types-requests>=2.31.0.6
Requires-Dist: npc-io>=0.1.24
Requires-Dist: codeocean>=0.3.1
Requires-Dist: aind-session>=0.3.4
Provides-Extra: polars
Requires-Dist: polars>1.0; extra == "polars"
Dynamic: license-file
